main.py
oppo_eap_mcp_server-0.1.2.dist-info/METADATA
oppo_eap_mcp_server-0.1.2.dist-info/WHEEL
oppo_eap_mcp_server-0.1.2.dist-info/entry_points.txt
oppo_eap_mcp_server-0.1.2.dist-info/top_level.txt
oppo_eap_mcp_server-0.1.2.dist-info/RECORD
