Metadata-Version: 2.4
Name: oppo-eap-mcp-server
Version: 0.1.2
Summary: Add your description here
Requires-Python: >=3.12
Requires-Dist: argparse>=1.4.0
Requires-Dist: mcp>=1.6.0
Requires-Dist: requests>=2.32.3
